gen3_metadata_templates/__init__.py
gen3_metadata_templates/props.py
gen3_metadata_templates/templates.py
gen3_metadata_templates-1.0.1.dist-info/LICENSE
gen3_metadata_templates-1.0.1.dist-info/METADATA
gen3_metadata_templates-1.0.1.dist-info/WHEEL
gen3_metadata_templates-1.0.1.dist-info/RECORD
