Metadata-Version: 2.3
Name: gen3_metadata_templates
Version: 1.0.1
Summary: Create Gen3 Metadata Submission Templates from a Gen3 JSON Schema
License: Apache 2.0
Author: JoshuaHarris391
Author-email: harjo391@gmail.com
Requires-Python: >=3.9.5
Classifier: License :: Other/Proprietary License
Classifier: Programming Language :: Python :: 3
Classifier: Programming Language :: Python :: 3.10
Classifier: Programming Language :: Python :: 3.11
Classifier: Programming Language :: Python :: 3.12
Classifier: Programming Language :: Python :: 3.13
Requires-Dist: gen3-validator (>=1.1.1,<2.0.0)
Requires-Dist: logging (>=0.4.9.6,<0.5.0.0)
Requires-Dist: openpyxl (>=3.1.5,<4.0.0)
Requires-Dist: pytest (>=8.4.1,<9.0.0)
Requires-Dist: xlsxwriter (>=3.2.5,<4.0.0)
